{"intents":[
    {"tag":"greeting", 
     "patterns":["سلام","چطوری","خوبی","چکار میکنی","حالت چطوره","سلاگ","سلامت باشی", "های"],
     "responses":["علیک سلامگ.","علیک سلام شما چطوری؟"],
     "context_set":""},
     {"tag":"meme", 
     "patterns":["میم","جوک"],
     "responses":["meme"],
     "context_set":""},
     {"tag":"estekhare", 
     "patterns":["استخاره"],
     "responses":["estekhare"],
     "context_set":""},
     {"tag":"shitpost", 
     "patterns":["شت پست","گه پست","عن پست"],
     "responses":["shitpost"],
     "context_set":""},
     {"tag":"wikipedia", 
     "patterns":["ویکی پدیا","توضیح","درباره"],
     "responses":["wikipedia"],
     "context_set":""},
     {"tag":"translate", 
     "patterns":["ترجمه","زبان"],
     "responses":["translate"],
     "context_set":""},
     {"tag":"shitranslate", 
     "patterns":["گوهجمه"],
     "responses":["shitranslate"],
     "context_set":""},
     {"tag":"spy", 
     "patterns":["جاسوس"],
     "responses":["spy"],
     "context_set":""},
     {"tag":"spystart", 
     "patterns":["شروع"],
     "responses":["spystart"],
     "context_set":""},
     {"tag":"goodnight", 
     "patterns":["شب بخیر", "شب خوش"],
     "responses":["goodnight"],
     "context_set":""},
     {"tag":"google", 
     "patterns":["گوگل"],
     "responses":["google"],
     "context_set":""}
]}